django_wait_for_databases/__init__.py
django_wait_for_databases/apps.py
django_wait_for_databases/management/commands/__init__.py
django_wait_for_databases/management/commands/wait_for_databases.py
django_wait_for_databases-0.0.2.dist-info/METADATA
django_wait_for_databases-0.0.2.dist-info/WHEEL
django_wait_for_databases-0.0.2.dist-info/licenses/LICENSE
django_wait_for_databases-0.0.2.dist-info/RECORD
