Metadata-Version: 2.3
Name: django-wait-for-databases
Version: 0.0.2
Summary: Django Wait For Databases
Project-URL: repository, https://github.com/lukewiwa/django-wait-for-databases
Author-email: lukewiwa <luke.wiwa@gmail.com>
License-Expression: MIT
License-File: LICENSE
Classifier: Framework :: Django
Classifier: License :: OSI Approved :: MIT License
Classifier: Operating System :: OS Independent
Classifier: Programming Language :: Python :: 3
Requires-Python: >=3.9
Requires-Dist: django>=4.2
